setup.py
jinziqi/__init__.py
jinziqi/jinziqi.py
jinziqi/jinziqi_chess.py
jinziqi.egg-info/PKG-INFO
jinziqi.egg-info/SOURCES.txt
jinziqi.egg-info/dependency_links.txt
jinziqi.egg-info/not-zip-safe
jinziqi.egg-info/top_level.txt