Metadata-Version: 1.0
Name: jinziqi
Version: 0.0.1.dev
Summary: jinziqi for python
Home-page: https://github.com/callsamleung/jinziqi_python
Author: samleung
Author-email: callsamleung@gmail.com
License: mit
Platform: UNKNOWN
